canopen_asyncio/__init__.py
canopen_asyncio/_version.py
canopen_asyncio/async_guard.py
canopen_asyncio/canopen.py
canopen_asyncio/emcy.py
canopen_asyncio/lss.py
canopen_asyncio/network.py
canopen_asyncio/nmt.py
canopen_asyncio/sync.py
canopen_asyncio/timestamp.py
canopen_asyncio/utils.py
canopen_asyncio/variable.py
canopen_asyncio/node/__init__.py
canopen_asyncio/node/base.py
canopen_asyncio/node/local.py
canopen_asyncio/node/remote.py
canopen_asyncio/objectdictionary/__init__.py
canopen_asyncio/objectdictionary/datatypes.py
canopen_asyncio/objectdictionary/eds.py
canopen_asyncio/objectdictionary/epf.py
canopen_asyncio/pdo/__init__.py
canopen_asyncio/pdo/base.py
canopen_asyncio/profiles/__init__.py
canopen_asyncio/profiles/p402.py
canopen_asyncio/profiles/tools/test_p402_states.py
canopen_asyncio/sdo/__init__.py
canopen_asyncio/sdo/base.py
canopen_asyncio/sdo/client.py
canopen_asyncio/sdo/constants.py
canopen_asyncio/sdo/exceptions.py
canopen_asyncio/sdo/server.py
canopen_asyncio-2.4.1.dist-info/METADATA
canopen_asyncio-2.4.1.dist-info/WHEEL
canopen_asyncio-2.4.1.dist-info/licenses/LICENSE.txt
canopen_asyncio-2.4.1.dist-info/RECORD
