Metadata-Version: 2.4
Name: canopen-asyncio
Version: 2.4.1
Summary: CANopen stack implementation for asyncio
Project-URL: documentation, https://canopen.readthedocs.io/en/stable/
Project-URL: repository, https://github.com/sveinse/canopen-asyncio
Author-email: Svein Seldal <sveinse@seldal.com>
License-Expression: MIT
License-File: LICENSE.txt
Classifier: Development Status :: 5 - Production/Stable
Classifier: Intended Audience :: Developers
Classifier: Operating System :: OS Independent
Classifier: Programming Language :: Python :: 3 :: Only
Classifier: Topic :: Scientific/Engineering
Requires-Python: >=3.9
Requires-Dist: python-can>=3.0.0
Provides-Extra: db-export
Requires-Dist: canmatrix~=1.0; extra == 'db-export'
